docker_volume_migrator/__init__.py
docker_volume_migrator/cli.py
docker_volume_migrator/core.py
docker_volume_migrator/utils.py
docker_volume_migrator-0.1.0.dist-info/licenses/LICENSE
docker_volume_migrator-0.1.0.dist-info/METADATA
docker_volume_migrator-0.1.0.dist-info/WHEEL
docker_volume_migrator-0.1.0.dist-info/entry_points.txt
docker_volume_migrator-0.1.0.dist-info/top_level.txt
docker_volume_migrator-0.1.0.dist-info/RECORD
