Metadata-Version: 2.4
Name: docker-volume-migrator
Version: 0.1.0
Summary: Interactive CLI utility to migrate Docker named volumes between hosts via SSH.
Author-email: djbios <djbios@djbios.org>
License: MIT License
Project-URL: Homepage, https://github.com/djbios/docker-volume-migrator
Project-URL: Source, https://github.com/djbios/docker-volume-migrator
Project-URL: Tracker, https://github.com/djbios/docker-volume-migrator/issues
Keywords: docker,cli,volume,migration,ssh
Classifier: Development Status :: 4 - Beta
Classifier: Environment :: Console
Classifier: Intended Audience :: Developers
Classifier: License :: OSI Approved :: MIT License
Classifier: Programming Language :: Python :: 3 :: Only
Classifier: Programming Language :: Python :: 3.9
Classifier: Programming Language :: Python :: 3.10
Classifier: Programming Language :: Python :: 3.11
Classifier: Topic :: System :: Systems Administration
Classifier: Topic :: Utilities
Requires-Python: >=3.9
License-File: LICENSE
Requires-Dist: typer>=0.16
Dynamic: license-file
